[
  {
    "id": 1,
    "tipo": "comida",
    "nome": "Maçã",
    "raridade": "comum",
    "descricao": "Uma maçã vermelha e brilhante. Parece deliciosa!",
    "fraseConsumo": "Mhmm! Que maçã deliciosa!",
    "modificadorSaude": 5,
    "modificadorFelicidade": 5,
    "modificadorFome": 5,
    "modificadorSujo": 0,
    "modificadorIdade": 0,
    "modificadorEnergia": 0,
    "modificadorIsSleeping": false,
    "precoCompra": 5,
    "precoVenda": 2
  },
  {
    "id": 2,
    "tipo": "erva",
    "nome": "Dente-de-leão",
    "raridade": "incomum",
    "descricao": "É valorizado por suas propriedades medicinais. Suas raízes, folhas e flores são frequentemente utilizadas na medicina tradicional para tratar uma variedade de condições, incluindo problemas digestivos, inflamação, problemas de pele e desintoxicação do fígado.",
    "fraseConsumo": "Eww! Podia ser mais gostoso...",
    "modificadorSaude": 20,
    "modificadorFelicidade": -2,
    "modificadorFome": -2,
    "modificadorSujo": 0,
    "modificadorIdade": 0,
    "modificadorEnergia": 0,
    "modificadorIsSleeping": false,
    "precoCompra": 5,
    "precoVenda": 2
  },
  {
    "id": 3,
    "tipo": "bebida",
    "nome": "Mel de Abelha Rainha",
    "raridade": "valioso",
    "descricao": "o Mel de Abelha Rainha é um verdadeiro tesouro culinário. Além de seu irresistível paladar, é apreciado por seus benefícios para a saúde, proporcionando uma dose de doçura e bem-estar.",
    "fraseConsumo": "Parece até nectar dos deuses!",
    "modificadorSaude": 10,
    "modificadorFelicidade": 20,
    "modificadorFome": 60,
    "modificadorSujo": 1,
    "modificadorIdade": 0,
    "modificadorEnergia": -1,
    "modificadorIsSleeping": false,
    "precoCompra": 0,
    "precoVenda": 0
  },
  {
    "id": 4,
    "tipo": "bebida",
    "nome": "Energético",
    "raridade": "comum",
    "descricao": "Com um pouco de Taurina, quem tomar esse veneno disfarçado de néctar vai ganhar muita energia.",
    "fraseConsumo": "Estou me sentindo ENERGIZADA!!",
    "modificadorSaude": -5,
    "modificadorFelicidade": 5,
    "modificadorFome": 1,
    "modificadorSujo": 0,
    "modificadorIdade": 0,
    "modificadorEnergia": 2,
    "modificadorIsSleeping": false,
    "precoCompra": 0,
    "precoVenda": 0
  },
  {
    "id": 5,
    "tipo": "comida",
    "nome": "Biscoito",
    "raridade": "comum",
    "descricao": "Biscoitos com gotas de chocolate.",
    "fraseConsumo": "Que delícia! As gotas de chocolate derretem mesmo na boca!",
    "modificadorSaude": 0,
    "modificadorFelicidade": 5,
    "modificadorFome": 3,
    "modificadorSujo": 0,
    "modificadorIdade": 0,
    "modificadorEnergia": 0,
    "modificadorIsSleeping": false,
    "precoCompra": 0,
    "precoVenda": 0
  }
]
